odoo/addons/website_sale_product_detail_attribute_image/README.rst
odoo/addons/website_sale_product_detail_attribute_image/__init__.py
odoo/addons/website_sale_product_detail_attribute_image/__manifest__.py
odoo/addons/website_sale_product_detail_attribute_image/controllers/__init__.py
odoo/addons/website_sale_product_detail_attribute_image/controllers/main.py
odoo/addons/website_sale_product_detail_attribute_image/data/demo.xml
odoo/addons/website_sale_product_detail_attribute_image/i18n/es.po
odoo/addons/website_sale_product_detail_attribute_image/i18n/website_sale_product_detail_attribute_image.pot
odoo/addons/website_sale_product_detail_attribute_image/models/__init__.py
odoo/addons/website_sale_product_detail_attribute_image/models/product_attribute.py
odoo/addons/website_sale_product_detail_attribute_image/readme/CONTRIBUTORS.rst
odoo/addons/website_sale_product_detail_attribute_image/readme/CREDITS.rst
odoo/addons/website_sale_product_detail_attribute_image/readme/DESCRIPTION.rst
odoo/addons/website_sale_product_detail_attribute_image/readme/USAGE.rst
odoo/addons/website_sale_product_detail_attribute_image/static/description/icon.png
odoo/addons/website_sale_product_detail_attribute_image/static/description/index.html
odoo/addons/website_sale_product_detail_attribute_image/static/src/img/EN374.png
odoo/addons/website_sale_product_detail_attribute_image/static/src/img/EN374_2003.png
odoo/addons/website_sale_product_detail_attribute_image/static/src/img/EN388.png
odoo/addons/website_sale_product_detail_attribute_image/static/src/js/website_sale_product_detail_attribute_image_tour.js
odoo/addons/website_sale_product_detail_attribute_image/static/src/less/style.less
odoo/addons/website_sale_product_detail_attribute_image/tests/__init__.py
odoo/addons/website_sale_product_detail_attribute_image/tests/test_website_sale_product_detail_attribute_image.py
odoo/addons/website_sale_product_detail_attribute_image/views/assets.xml
odoo11_addon_website_sale_product_detail_attribute_image-11.0.1.1.1.dist-info/METADATA
odoo11_addon_website_sale_product_detail_attribute_image-11.0.1.1.1.dist-info/WHEEL
odoo11_addon_website_sale_product_detail_attribute_image-11.0.1.1.1.dist-info/top_level.txt
odoo11_addon_website_sale_product_detail_attribute_image-11.0.1.1.1.dist-info/RECORD
